ajobot_manager/__init__.py
ajobot_manager/manager.py
ajobot_manager-1.2.3.dist-info/LICENSE
ajobot_manager-1.2.3.dist-info/METADATA
ajobot_manager-1.2.3.dist-info/WHEEL
ajobot_manager-1.2.3.dist-info/RECORD
